pyautomaton/__init__.py
pyautomaton/automaton.py
pyautomaton-0.2.2.dist-info/WHEEL
pyautomaton-0.2.2.dist-info/METADATA
pyautomaton-0.2.2.dist-info/RECORD
