Metadata-Version: 2.1
Name: pyautomaton
Version: 0.2.2
Summary: a simple library to define reusable Finite State Machines with a fluent delcarative style
Home-page: https://github.com/Cirius1792/pyfsm
License: MIT
Author: cirius1792
Author-email: cirolucio.tecce@gmail.com
Requires-Python: >=3.8,<4.0
Classifier: License :: OSI Approved :: MIT License
Classifier: Programming Language :: Python :: 3
Classifier: Programming Language :: Python :: 3.8
Classifier: Programming Language :: Python :: 3.9
Classifier: Programming Language :: Python :: 3.10
Project-URL: Repository, https://github.com/Cirius1792/pyfsm
